{"composable_web_language.md":"d0ecf64f","composable_web_networkinformation.md":"eee688fb","composable_web_online.md":"3186842e","composable_web_pagevisibility.md":"ea79b145","composable_web_share.md":"5d08f9de","composable_web_timeout.md":"4250951a","composable_web_websocket.md":"a6f4394b","composable_web_worker.md":"39c0cede","composable_web_workerfunction.md":"acf44be7","guide_index.md":"9f084cd8","guide_why.md":"98505482","index.md":"07a3c6fc","composable_storage_storage.md":"b423da15","composable_storage_sessionstorage.md":"bfbcd1bb","composable_web_intersectionobserver.md":"4270e483","composable_breakpoint_breakpoint.md":"7367658a","composable_breakpoint_chrome.md":"bb6bd5a6","composable_data_date.md":"83803c84","composable_data_now.md":"039d0230","composable_data_performance.md":"50ec863f","composable_event_mouse.md":"708cc6ec","composable_event_mouseinelement.md":"18eed315","composable_event_mousemove.md":"15e717c8","composable_event_outsidepress.md":"9cc3749e","composable_event_resize.md":"76aeb7d9","composable_event_scroll.md":"c25a14a6","composable_format_format.md":"1ca36125","composable_format_path.md":"56f213ea","composable_meta_title.md":"714af532","composable_misc_inject.md":"824b8b15","composable_misc_interval.md":"ec29487e","composable_misc_lockscroll.md":"fd60950b","composable_misc_model.md":"f352e8dd","composable_misc_refdebounced.md":"e5034dea","composable_misc_refshared.md":"6427e203","composable_misc_sharedref.md":"53995cef","composable_pagination_pagination.md":"5c9b716c","composable_promise_cancellablepromise.md":"6792c4a8","composable_promise_lazypromise.md":"d24f1a2c","composable_promise_promise.md":"17e31102","composable_promise_retry.md":"d3f7bfd5","composable_state_timeline.md":"b66827f1","composable_state_undo.md":"d9b11e06","composable_storage_localstorage.md":"4aced13b","composable_validation_validation.md":"9320a47d","composable_web_broadcastchannel.md":"f4ca3c30","composable_web_clipboard.md":"e3079633","composable_misc_matchmedia.md":"e76e2008","composable_pagination_arraypagination.md":"8c96654d","composable_state_valuesync.md":"23c918f2","composable_web_cssvariables.md":"d57f8617","composable_storage_webstorage.md":"e7dbda6d","composable_web_fetch.md":"3b605cf0","composable_web_geolocation.md":"848b3d03"}
